filebus/__init__.py
filebus-0.3.5.data/data/libexec/filebus/bash-import.bash
filebus-0.3.5.data/data/libexec/filebus/filebus-test.bash
filebus-0.3.5.data/data/libexec/filebus/filebus.bash
filebus-0.3.5.data/data/libexec/filebus/log.bash
filebus-0.3.5.data/data/libexec/filebus/signal.bash
filebus-0.3.5.data/data/libexec/filebus/supervisor.bash
filebus-0.3.5.dist-info/LICENSE
filebus-0.3.5.dist-info/METADATA
filebus-0.3.5.dist-info/WHEEL
filebus-0.3.5.dist-info/entry_points.txt
filebus-0.3.5.dist-info/top_level.txt
filebus-0.3.5.dist-info/RECORD
