Metadata-Version: 2.1
Name: filebus
Version: 0.3.5
Summary: A user space multicast named pipe implementation backed by a regular file
Home-page: https://github.com/pipebus/filebus
Author: Zac Medico
Author-email: <zmedico@gmail.com>
License: UNKNOWN
Project-URL: Bug Tracker, https://github.com/pipebus/filebus/issues
Platform: UNKNOWN
Classifier: License :: OSI Approved :: Apache Software License
Classifier: Operating System :: POSIX
Classifier: Programming Language :: Python :: 3
Classifier: Programming Language :: Unix Shell
Requires-Python: >=3.6
License-File: LICENSE
Requires-Dist: filelock
